[
  {
    "text": "migration",
    "id": "cp0.0",
    "type": "cited",
    "from": "[2005]"
  },
  {
    "text": "refugee review tribunal",
    "id": "cp0.1",
    "type": "cited",
    "from": "[2005]"
  },
  {
    "text": "protection visa",
    "id": "cp0.2",
    "type": "cited",
    "from": "[2005]"
  },
  {
    "text": "order nisi",
    "id": "cp0.3",
    "type": "cited",
    "from": "[2005]"
  },
  {
    "text": "high court proceedings remitted to federal magistrates court",
    "id": "cp0.4",
    "type": "cited",
    "from": "[2005]"
  },
  {
    "text": "whether final order should be made",
    "id": "cp0.5",
    "type": "cited",
    "from": "[2005]"
  },
  {
    "text": "application dismissed rather than order nisi refused.",
    "id": "cp0.6",
    "type": "cited",
    "from": "[2005]"
  },
  {
    "text": "muin v refugee review tribunal  lie v refugee review tribunal  administrative law",
    "id": "cp1.0",
    "type": "cited",
    "from": "[2002]"
  },
  {
    "text": "constitutional writs",
    "id": "cp1.1",
    "type": "cited",
    "from": "[2002]"
  },
  {
    "text": "procedural fairness",
    "id": "cp1.2",
    "type": "cited",
    "from": "[2002]"
  },
  {
    "text": "alleged failure to have regard to relevant documents",
    "id": "cp1.3",
    "type": "cited",
    "from": "[2002]"
  },
  {
    "text": "alleged failure to provide reasonable opportunity to respond to adverse material",
    "id": "cp1.4",
    "type": "cited",
    "from": "[2002]"
  },
  {
    "text": "jurisdictional error for denial of procedural fairness and natural justice.  immigration",
    "id": "cp1.5",
    "type": "cited",
    "from": "[2002]"
  },
  {
    "text": "refugee",
    "id": "cp1.6",
    "type": "cited",
    "from": "[2002]"
  },
  {
    "text": "protection visa",
    "id": "cp1.7",
    "type": "cited",
    "from": "[2002]"
  },
  {
    "text": "decision by minister to refuse application for visa",
    "id": "cp1.8",
    "type": "cited",
    "from": "[2002]"
  },
  {
    "text": "review of decision by refugee review tribunal",
    "id": "cp1.9",
    "type": "cited",
    "from": "[2002]"
  },
  {
    "text": "obligation of secretary of department of immigration and multicultural affairs to give relevant documents to registrar of tribunal for purpose of review",
    "id": "cp1.10",
    "type": "cited",
    "from": "[2002]"
  },
  {
    "text": "nature and extent of obligation",
    "id": "cp1.11",
    "type": "cited",
    "from": "[2002]"
  },
  {
    "text": "migration act 1958 (cth), ss 418(3) , 424 (1).  constitutional law (cth)",
    "id": "cp1.12",
    "type": "cited",
    "from": "[2002]"
  },
  {
    "text": "high court",
    "id": "cp1.13",
    "type": "cited",
    "from": "[2002]"
  },
  {
    "text": "federal court",
    "id": "cp1.14",
    "type": "cited",
    "from": "[2002]"
  },
  {
    "text": "review of administrative decision by officers of the commonwealth",
    "id": "cp1.15",
    "type": "cited",
    "from": "[2002]"
  },
  {
    "text": "migration",
    "id": "cp1.16",
    "type": "cited",
    "from": "[2002]"
  },
  {
    "text": "refusal to grant protection visa to claimant for refugee status",
    "id": "cp1.17",
    "type": "cited",
    "from": "[2002]"
  },
  {
    "text": "requirement of procedural fairness",
    "id": "cp1.18",
    "type": "cited",
    "from": "[2002]"
  },
  {
    "text": "alleged failure to have regard to relevant documents",
    "id": "cp1.19",
    "type": "cited",
    "from": "[2002]"
  },
  {
    "text": "alleged failure to provide reasonable opportunity to respond to adverse materials",
    "id": "cp1.20",
    "type": "cited",
    "from": "[2002]"
  },
  {
    "text": "jurisdictional error",
    "id": "cp1.21",
    "type": "cited",
    "from": "[2002]"
  },
  {
    "text": "availability of constitutional relief under s 75(v) and other relief for denial of procedural fairness and natural justice.",
    "id": "cp1.22",
    "type": "cited",
    "from": "[2002]"
  },
  {
    "text": "administrative law",
    "id": "cp4.0",
    "type": "cited",
    "from": "[1990]"
  },
  {
    "text": "natural justice",
    "id": "cp4.1",
    "type": "cited",
    "from": "[1990]"
  },
  {
    "text": "bias",
    "id": "cp4.2",
    "type": "cited",
    "from": "[1990]"
  },
  {
    "text": "rule of necessity.  broadcasting",
    "id": "cp4.3",
    "type": "cited",
    "from": "[1990]"
  },
  {
    "text": "australian broadcasting tribunal",
    "id": "cp4.4",
    "type": "cited",
    "from": "[1990]"
  },
  {
    "text": "powers",
    "id": "cp4.5",
    "type": "cited",
    "from": "[1990]"
  },
  {
    "text": "programme standards",
    "id": "cp4.6",
    "type": "cited",
    "from": "[1990]"
  },
  {
    "text": "enforcement",
    "id": "cp4.7",
    "type": "cited",
    "from": "[1990]"
  },
  {
    "text": "power to prohibit person from broadcasting",
    "id": "cp4.8",
    "type": "cited",
    "from": "[1990]"
  },
  {
    "text": "power to impose restrictions",
    "id": "cp4.9",
    "type": "cited",
    "from": "[1990]"
  },
  {
    "text": "findings",
    "id": "cp4.10",
    "type": "cited",
    "from": "[1990]"
  },
  {
    "text": "opportunity to show cause",
    "id": "cp4.11",
    "type": "cited",
    "from": "[1990]"
  },
  {
    "text": "broadcasting act 1942 (cth), s. 119.",
    "id": "cp4.12",
    "type": "cited",
    "from": "[1990]"
  },
  {
    "text": "negligence",
    "id": "cp5.0",
    "type": "cited",
    "from": "[1959]"
  },
  {
    "text": "action",
    "id": "cp5.1",
    "type": "cited",
    "from": "[1959]"
  },
  {
    "text": "collision between motor vehicles",
    "id": "cp5.2",
    "type": "cited",
    "from": "[1959]"
  },
  {
    "text": "no direct evidence of negligence",
    "id": "cp5.3",
    "type": "cited",
    "from": "[1959]"
  },
  {
    "text": "matter of inference from proved facts",
    "id": "cp5.4",
    "type": "cited",
    "from": "[1959]"
  },
  {
    "text": "sufficiency of facts to support inference.  practice",
    "id": "cp5.5",
    "type": "cited",
    "from": "[1959]"
  },
  {
    "text": "direction to jury",
    "id": "cp5.6",
    "type": "cited",
    "from": "[1959]"
  },
  {
    "text": "inference of negligence open on proved circumstances",
    "id": "cp5.7",
    "type": "cited",
    "from": "[1959]"
  },
  {
    "text": "whether inference should be drawn",
    "id": "cp5.8",
    "type": "cited",
    "from": "[1959]"
  },
  {
    "text": "defendant able to explain facts from &amp;which inference sought to be drawn",
    "id": "cp5.9",
    "type": "cited",
    "from": "[1959]"
  },
  {
    "text": "failure of defendant to give evidence",
    "id": "cp5.10",
    "type": "cited",
    "from": "[1959]"
  },
  {
    "text": "what reliance to be placed by jury on such failure in deciding whether or not to draw inference",
    "id": "cp5.11",
    "type": "cited",
    "from": "[1959]"
  },
  {
    "text": "nature of direction to jury.  practice",
    "id": "cp5.12",
    "type": "cited",
    "from": "[1959]"
  },
  {
    "text": "non-suit",
    "id": "cp5.13",
    "type": "cited",
    "from": "[1959]"
  },
  {
    "text": "verdict by direction",
    "id": "cp5.14",
    "type": "cited",
    "from": "[1959]"
  },
  {
    "text": "history",
    "id": "cp5.15",
    "type": "cited",
    "from": "[1959]"
  },
  {
    "text": "application in new south wales.",
    "id": "cp5.16",
    "type": "cited",
    "from": "[1959]"
  }
]