[
  {
    "text": "copyright",
    "id": "cp1.0",
    "type": "citing",
    "from": "[2009]"
  },
  {
    "text": "copyright infringement in gaming machines parts and components",
    "id": "cp1.1",
    "type": "citing",
    "from": "[2009]"
  },
  {
    "text": "infringement inferred from circumstantial evidence",
    "id": "cp1.2",
    "type": "citing",
    "from": "[2009]"
  },
  {
    "text": "burden of proof",
    "id": "cp1.3",
    "type": "citing",
    "from": "[2009]"
  },
  {
    "text": "authorisation of copyright infringement",
    "id": "cp1.4",
    "type": "citing",
    "from": "[2009]"
  },
  {
    "text": "joint liability",
    "id": "cp1.5",
    "type": "citing",
    "from": "[2009]"
  },
  {
    "text": "claim in conversion for resale of components acquired from scrap dealer fails",
    "id": "cp1.6",
    "type": "citing",
    "from": "[2009]"
  },
  {
    "text": "scrap dealer not a bailee of the goods",
    "id": "cp1.7",
    "type": "citing",
    "from": "[2009]"
  },
  {
    "text": "infringement of copyright established",
    "id": "cp1.8",
    "type": "citing",
    "from": "[2009]"
  },
  {
    "text": "damages and additional damages ordered.",
    "id": "cp1.9",
    "type": "citing",
    "from": "[2009]"
  },
  {
    "text": "intellectual property",
    "id": "cp3.0",
    "type": "citing",
    "from": "[2007]"
  },
  {
    "text": "copyright",
    "id": "cp3.1",
    "type": "citing",
    "from": "[2007]"
  },
  {
    "text": "assessment of damages",
    "id": "cp3.2",
    "type": "citing",
    "from": "[2007]"
  },
  {
    "text": "election for compensatory damages",
    "id": "cp3.3",
    "type": "citing",
    "from": "[2007]"
  },
  {
    "text": "assessment of damages on the basis of a royalty inappropriate",
    "id": "cp3.4",
    "type": "citing",
    "from": "[2007]"
  },
  {
    "text": "whether loss of sales by the copyright owner could be inferred merely from the fact of sales of infringing product",
    "id": "cp3.5",
    "type": "citing",
    "from": "[2007]"
  },
  {
    "text": "requirement for evidence of lost sales and value of such sales",
    "id": "cp3.6",
    "type": "citing",
    "from": "[2007]"
  },
  {
    "text": "additional damages",
    "id": "cp3.7",
    "type": "citing",
    "from": "[2007]"
  },
  {
    "text": "purpose of awarding additional damages",
    "id": "cp3.8",
    "type": "citing",
    "from": "[2007]"
  },
  {
    "text": "assessment of additional damages",
    "id": "cp3.9",
    "type": "citing",
    "from": "[2007]"
  },
  {
    "text": "practice and procedure",
    "id": "cp4.0",
    "type": "citing",
    "from": "[2006]"
  },
  {
    "text": "costs",
    "id": "cp4.1",
    "type": "citing",
    "from": "[2006]"
  },
  {
    "text": "whether partial costs order should be made in a case where the award of damages was well short of the amount claimed by the applicants but exceeded an offer made by the respondents",
    "id": "cp4.2",
    "type": "citing",
    "from": "[2006]"
  },
  {
    "text": "whether the costs associated with the evidence of an expert should be excluded in a case where the experts' opinions were unsupported by any evidence.",
    "id": "cp4.3",
    "type": "citing",
    "from": "[2006]"
  }
]