[
  {
    "text": "legal practitioners",
    "id": "cp0.0",
    "type": "cited",
    "from": "[2006]"
  },
  {
    "text": "application to restrain solicitor from acting for party to the proceedings",
    "id": "cp0.1",
    "type": "cited",
    "from": "[2006]"
  },
  {
    "text": "relevant legal principles",
    "id": "cp0.2",
    "type": "cited",
    "from": "[2006]"
  },
  {
    "text": "inherent jurisdiction of the court to restrain solicitor from acting if it is in the interests of justice",
    "id": "cp0.3",
    "type": "cited",
    "from": "[2006]"
  },
  {
    "text": "whether fair-minded, reasonably informed member of the public would conclude that proper administration of justice requires that solicitor be restrained",
    "id": "cp0.4",
    "type": "cited",
    "from": "[2006]"
  },
  {
    "text": "where solicitor acting for joint venture company and interests of certain directors",
    "id": "cp0.5",
    "type": "cited",
    "from": "[2006]"
  },
  {
    "text": "where proceedings involve disputes between various interest-holders in joint venture",
    "id": "cp0.6",
    "type": "cited",
    "from": "[2006]"
  }
]